server.py
feiyu_mcp_server_demo-0.1.1.dist-info/METADATA
feiyu_mcp_server_demo-0.1.1.dist-info/WHEEL
feiyu_mcp_server_demo-0.1.1.dist-info/top_level.txt
feiyu_mcp_server_demo-0.1.1.dist-info/RECORD
