Metadata-Version: 2.4
Name: feiyu-mcp-server-demo
Version: 0.1.1
Summary: Add your description here
Requires-Python: >=3.12.9
Requires-Dist: mcp[cli]>=1.9.2
